pgflow/PIDcontroller.py
pgflow/__init__.py
pgflow/arena.py
pgflow/building.py
pgflow/cases.py
pgflow/dynamics.py
pgflow/main.py
pgflow/panel_flow.py
pgflow/plotting/__init__.py
pgflow/plotting/animation/__init__.py
pgflow/plotting/animation/animation.py
pgflow/plotting/drone_interactions/__init__.py
pgflow/plotting/drone_interactions/collision_handler.py
pgflow/plotting/drone_interactions/connecting_lines.py
pgflow/plotting/drone_interactions/distance_manager.py
pgflow/plotting/entities/__init__.py
pgflow/plotting/entities/arrow.py
pgflow/plotting/entities/building.py
pgflow/plotting/entities/drone.py
pgflow/plotting/entities/path.py
pgflow/plotting/entities/warning_circle.py
pgflow/plotting/graphics/__init__.py
pgflow/plotting/graphics/arrow_graphics.py
pgflow/plotting/graphics/building_graphics.py
pgflow/plotting/graphics/connecting_line_graphics.py
pgflow/plotting/graphics/drone_graphics.py
pgflow/plotting/graphics/path_graphics.py
pgflow/plotting/main_plot.py
pgflow/plotting/observer_utils.py
pgflow/plotting/ui_components.py
pgflow/plotting/utils.py
pgflow/utils/__init__.py
pgflow/utils/json_utils.py
pgflow/utils/plot_utils.py
pgflow/utils/simulation_utils.py
pgflow/vehicle.py
pgflow-0.3.1.dist-info/LICENSE
pgflow-0.3.1.dist-info/METADATA
pgflow-0.3.1.dist-info/WHEEL
pgflow-0.3.1.dist-info/entry_points.txt
pgflow-0.3.1.dist-info/RECORD
